README.md
setup.py
tinycache/__init__.py
tinycache.egg-info/PKG-INFO
tinycache.egg-info/SOURCES.txt
tinycache.egg-info/dependency_links.txt
tinycache.egg-info/top_level.txt