Metadata-Version: 2.1
Name: tinycache
Version: 0.1.3
Summary: tinycache a python modules base on local file for any python data struct
Home-page: https://github.com/jamesqin-cn/tinycache
Author: jamesqin
Author-email: jamesqin@vip.qq.com
License: MIT
Platform: any
Classifier: Intended Audience :: Developers
Classifier: Operating System :: OS Independent
Classifier: Topic :: Utilities
Classifier: Topic :: Software Development :: Libraries :: Python Modules
Classifier: Programming Language :: Python
Classifier: Programming Language :: Python :: 2
Classifier: Programming Language :: Python :: 2.7
Classifier: Programming Language :: Python :: 3
Classifier: Programming Language :: Python :: 3.7
